nonebot_plugin_bfvsearch/__init__.py
nonebot_plugin_bfvsearch-0.1.8.dist-info/LICENSE
nonebot_plugin_bfvsearch-0.1.8.dist-info/METADATA
nonebot_plugin_bfvsearch-0.1.8.dist-info/WHEEL
nonebot_plugin_bfvsearch-0.1.8.dist-info/top_level.txt
nonebot_plugin_bfvsearch-0.1.8.dist-info/RECORD
