Metadata-Version: 2.1
Name: nonebot_plugin_bfvsearch
Version: 0.1.8
Summary: 基于 Nonebot2 的战地 5 QQ 群查询插件。
Author-email: Swallow513 <3214115907@qq.com>
Classifier: Programming Language :: Python :: 3
Classifier: License :: OSI Approved :: MIT License
Classifier: Operating System :: OS Independent
Requires-Python: >=3.8
License-File: LICENSE
Requires-Dist: nonebot2>=2.2.0
Requires-Dist: aiohttp>=3.10.6
Requires-Dist: aiocache>=0.12.3
Requires-Dist: nonebot-plugin-htmlrender>=0.3.0
Requires-Dist: nonebot-adapter-onebot>=2.2.0
Requires-Dist: pytz>=2024.2
